nautc-1.1.2.dist-info/METADATA
nautc-1.1.2.dist-info/WHEEL
nautc-1.1.2.dist-info/entry_points.txt
nautc.py
txt.gz
nautc-1.1.2.dist-info/RECORD
