Metadata-Version: 2.1
Name: nautc
Version: 1.1.2
Summary: Convert plain text (letters, sometimes numbers, sometimes punctuation) to obscure but cool characters.
Author-Email: Nasy <nasyxx+python@gmail.com>
License: MIT
Requires-Python: <4.0,>=3.10
Requires-Dist: tyro>=0.7.3
